admin/__init__.py
admin/agent_config_manager.py
admin/common.py
admin/config_manager.py
admin/event_reporter.py
admin/sign_msg.py
agent_admin-0.1.1.data/scripts/manage_config
agent_admin-0.1.1.data/scripts/msg_signer
agent_admin-0.1.1.data/scripts/run_report
agent_admin-0.1.1.dist-info/DESCRIPTION.rst
agent_admin-0.1.1.dist-info/METADATA
agent_admin-0.1.1.dist-info/RECORD
agent_admin-0.1.1.dist-info/WHEEL
agent_admin-0.1.1.dist-info/metadata.json
agent_admin-0.1.1.dist-info/top_level.txt
